snappylapy/__init__.py
snappylapy/_cli.py
snappylapy/_plugin.py
snappylapy/_utils_directories.py
snappylapy/constants.py
snappylapy/exceptions.py
snappylapy/fixtures.py
snappylapy/marker.py
snappylapy/models.py
snappylapy/py.typed
snappylapy/serialization.py
snappylapy/session.py
snappylapy/expectation_classes/__init__.py
snappylapy/expectation_classes/base_snapshot.py
snappylapy/expectation_classes/expect_bytes.py
snappylapy/expectation_classes/expect_dataframe.py
snappylapy/expectation_classes/expect_dict.py
snappylapy/expectation_classes/expect_list.py
snappylapy/expectation_classes/expect_object.py
snappylapy/expectation_classes/expect_string.py
snappylapy-0.10.0.dist-info/licenses/LICENSE
snappylapy-0.10.0.dist-info/METADATA
snappylapy-0.10.0.dist-info/WHEEL
snappylapy-0.10.0.dist-info/entry_points.txt
snappylapy-0.10.0.dist-info/top_level.txt
snappylapy-0.10.0.dist-info/RECORD
