Metadata-Version: 2.4
Name: snappylapy
Version: 0.10.0
Summary: A snapshot library for python optimized for easy of use, human readable snapshots and enabling decoupling of chained integration tests.
Author: Martin Møldrup
Project-URL: Homepage, https://martinmoldrup.github.io/snappylapy
Project-URL: Documentation, https://martinmoldrup.github.io/snappylapy
Project-URL: Repository, https://github.com/martinmoldrup/snappylapy
Project-URL: Issues, https://github.com/martinmoldrup/snappylapy/issues
Project-URL: Changelog, https://github.com/martinmoldrup/snappylapy/blob/master/CHANGELOG.md
Keywords: pytest,snapshot,testing,snapshot-testing,integration-testing,unit-testing
Classifier: Framework :: Pytest
Classifier: Development Status :: 4 - Beta
Classifier: Intended Audience :: Developers
Classifier: Topic :: Software Development :: Testing
Classifier: Operating System :: OS Independent
Classifier: Programming Language :: Python
Classifier: Programming Language :: Python :: 3.10
Classifier: Programming Language :: Python :: 3.11
Classifier: Programming Language :: Python :: 3.12
Classifier: Programming Language :: Python :: 3.13
Classifier: Programming Language :: Python :: 3.14
Classifier: Programming Language :: Python :: 3 :: Only
Classifier: Programming Language :: Python :: Implementation :: CPython
Classifier: Programming Language :: Python :: Implementation :: PyPy
Classifier: License :: OSI Approved :: GNU General Public License v3 (GPLv3)
Requires-Python: <4.0,>=3.9
License-File: LICENSE
Requires-Dist: pytest>=7.0
Requires-Dist: jsonpickle>=1.0
Requires-Dist: typer
Requires-Dist: levenshtein>=0.27.1
Requires-Dist: toolit>=0.5.0
Provides-Extra: pandas
Requires-Dist: pandas; extra == "pandas"
Provides-Extra: all
Requires-Dist: pandas; extra == "all"
Dynamic: license-file
